{
    "$schema": "https://biomejs.dev/schemas/1.8.3/schema.json",
    "formatter": {
        "enabled": true,
        "formatWithErrors": false,
        "indentStyle": "space",
        "indentWidth": 4,
        "lineEnding": "lf",
        "lineWidth": 80,
        "attributePosition": "auto",
        "ignore": [
            "app/grandchallenge/core/static/vendored/*",
            "app/grandchallenge/core/static/js/markdownx.js",
            "app/grandchallenge/core/static/js/world-atlas/countries-110m.json",
            "app/grandchallenge/core/static/css/select2-bootstrap4-theme/select2-bootstrap4.css",
            "app/grandchallenge/core/static/css/select2-bootstrap4-theme/select2-bootstrap4.min.css",
            "**/*.html",
            "**/*.md"
        ]
    },
    "organizeImports": { "enabled": true },
    "linter": { "enabled": true, "rules": { "recommended": true } },
    "javascript": {
        "formatter": {
            "jsxQuoteStyle": "double",
            "quoteProperties": "asNeeded",
            "trailingCommas": "all",
            "semicolons": "asNeeded",
            "arrowParentheses": "always",
            "bracketSpacing": true,
            "bracketSameLine": false,
            "quoteStyle": "single",
            "attributePosition": "auto"
        }
    }
}
